mtgtools-0.9.63-py3.11-nspkg.pth
mtgtools/MtgDB.py
mtgtools/PCard.py
mtgtools/PCardList.py
mtgtools/PSet.py
mtgtools/PSetList.py
mtgtools/util/__init__.py
mtgtools/util/api_requests.py
mtgtools-0.9.63.dist-info/LICENSE.txt
mtgtools-0.9.63.dist-info/METADATA
mtgtools-0.9.63.dist-info/WHEEL
mtgtools-0.9.63.dist-info/namespace_packages.txt
mtgtools-0.9.63.dist-info/top_level.txt
mtgtools-0.9.63.dist-info/RECORD
