Metadata-Version: 2.1
Name: mtgtools
Version: 0.9.63
Summary: Collection of tools for easy handling of Magic: The Gathering card and set data on your computer from Scryfall and/or magicthegathering.io.
Home-page: https://github.com/EskoSalaka/mtgtools
Author: Esko-Kalervo Salaka
Author-email: esko.salaka@gmail.com
Classifier: Programming Language :: Python :: 3.5
Classifier: License :: OSI Approved :: Zope Public License
Classifier: Operating System :: OS Independent
Classifier: Topic :: Software Development :: Libraries :: Python Modules
License-File: LICENSE.txt
Requires-Dist: ZODB
Requires-Dist: requests
Requires-Dist: Pillow
